b10_tcache/__init__.py
b10_tcache/archive.py
b10_tcache/core.py
b10_tcache/environment.py
b10_tcache/info.py
b10_tcache/utils.py
b10_tcache-1.0.3.dist-info/METADATA
b10_tcache-1.0.3.dist-info/WHEEL
b10_tcache-1.0.3.dist-info/RECORD
